suddenly/__init__.py
suddenly/suddenly.py
suddenly-0.1.3.1.dist-info/entry_points.txt
suddenly-0.1.3.1.dist-info/LICENSE
suddenly-0.1.3.1.dist-info/WHEEL
suddenly-0.1.3.1.dist-info/METADATA
suddenly-0.1.3.1.dist-info/RECORD
